cstar/__init__.py
cstar/args.py
cstar/cleanup.py
cstar/command.py
cstar/cstarcli.py
cstar/cstarparcli.py
cstar/endpoint_mapping.py
cstar/exceptions.py
cstar/executionresult.py
cstar/job.py
cstar/jobprinter.py
cstar/jobreader.py
cstar/jobrunner.py
cstar/jobwriter.py
cstar/output.py
cstar/progress.py
cstar/remote.py
cstar/remote_paramiko.py
cstar/signalhandler.py
cstar/state.py
cstar/strategy.py
cstar/topology.py
cstar/nodetoolparser/__init__.py
cstar/nodetoolparser/describering.py
cstar/nodetoolparser/simple.py
cstar/nodetoolparser/status.py
cstar/resources/__init__.py
cstar/resources/commands/run.sh
cstar/resources/scripts/remote_job.sh
cstar-0.9.0.dist-info/LICENSE
cstar-0.9.0.dist-info/METADATA
cstar-0.9.0.dist-info/NOTICE
cstar-0.9.0.dist-info/WHEEL
cstar-0.9.0.dist-info/entry_points.txt
cstar-0.9.0.dist-info/top_level.txt
cstar-0.9.0.dist-info/RECORD
