Metadata-Version: 2.1
Name: cstar
Version: 0.9.0
Summary: Apache Cassandra cluster orchestration tool for the command line
Home-page: https://github.com/spotify/cstar
Author: Spotify
Author-email: rebase-squad@spotify.com
License: Apache-2.0
Platform: UNKNOWN
Classifier: Development Status :: 4 - Beta
Classifier: Environment :: Console
Classifier: Intended Audience :: System Administrators
Classifier: License :: OSI Approved :: Apache Software License
Classifier: Programming Language :: Python :: 3.6
Classifier: Topic :: Database
Requires-Python: >=3
Requires-Dist: paramiko (~=2.7)
